openapi/__init__.py
openapi/api_client.py
openapi/api_response.py
openapi/configuration.py
openapi/exceptions.py
openapi/rest.py
openapi/api/__init__.py
openapi/api/auth_api.py
openapi/api/catalog_products_api.py
openapi/api/contracts_api.py
openapi/api/credits_api.py
openapi/api/customers_api.py
openapi/api/events_api.py
openapi/api/invoices_api.py
openapi/api/measurements_api.py
openapi/api/meters_api.py
openapi/api/product_consumptions_api.py
openapi/api/webhooks_api.py
openapi/models/__init__.py
openapi/models/address.py
openapi/models/aggregation_method.py
openapi/models/aggregation_operator.py
openapi/models/billing_cycle_status.py
openapi/models/condition.py
openapi/models/contact.py
openapi/models/create_catalog_product_request.py
openapi/models/create_catalog_product_response.py
openapi/models/create_catalog_product_response_catalog_product.py
openapi/models/create_contract_request.py
openapi/models/create_contract_response.py
openapi/models/create_customer_request.py
openapi/models/create_customer_response.py
openapi/models/create_customer_response_customer.py
openapi/models/create_measurement_request.py
openapi/models/create_measurement_request_usage_date.py
openapi/models/create_measurement_response.py
openapi/models/create_measurement_response_measurement.py
openapi/models/credit_ledger_entry.py
openapi/models/criterion.py
openapi/models/criterion_operator.py
openapi/models/customer_source.py
openapi/models/deduct_credits_request.py
openapi/models/delete_catalog_product_response.py
openapi/models/delete_catalog_product_response_catalog_product.py
openapi/models/delete_contract_response.py
openapi/models/delete_contract_response_contract.py
openapi/models/delete_customer_response.py
openapi/models/delete_customer_response_customer.py
openapi/models/delete_event_response.py
openapi/models/delete_event_response_event.py
openapi/models/delete_events_by_refs_request.py
openapi/models/delete_events_by_refs_response.py
vayu_client-1.0.13.dist-info/licenses/LICENSE
vayu_client-1.0.13.dist-info/METADATA
vayu_client-1.0.13.dist-info/WHEEL
vayu_client-1.0.13.dist-info/top_level.txt
vayu_client-1.0.13.dist-info/RECORD
